{
  "type": "Collection",
  "stac_version": "1.0.0",
  "id": "01KD1ED4SMM60CSXT77RVMNS7C",
  "title": "Bay of Plenty - Ōpōtiki to Tōrere Coastal LiDAR 10m DEM (2025)",
  "description": "Coastal Digital Elevation Model within the Bay of Plenty region captured in 2025.",
  "license": "CC-BY-4.0",
  "links": [
    {
      "rel": "root",
      "href": "https://nz-coastal.s3.ap-southeast-2.amazonaws.com/catalog.json",
      "type": "application/json"
    },
    { "rel": "self", "href": "./collection.json", "type": "application/json" },
    {
      "href": "./BE41.json",
      "rel": "item",
      "type": "application/geo+json",
      "file:checksum": "1220dcdccbf115713794f70c172e2310c8cf504119b1a23039afa0214c2d82be1739"
    },
    {
      "href": "./BE42.json",
      "rel": "item",
      "type": "application/geo+json",
      "file:checksum": "12204de3b158d836dc4af1d0174d62f821669d6bd678b4ff10c4768f2f0ffdfb2c3d"
    }
  ],
  "providers": [
    { "name": "Toitū Te Whenua Land Information New Zealand", "roles": ["host", "licensor", "processor"] },
    { "name": "Woolpert", "roles": ["producer"] }
  ],
  "linz:lifecycle": "completed",
  "linz:geospatial_category": "dem",
  "linz:region": "bay-of-plenty",
  "linz:security_classification": "unclassified",
  "linz:slug": "opotiki-to-torere_2025",
  "gsd": 10,
  "created": "2025-12-21T21:52:47Z",
  "updated": "2025-12-21T21:52:47Z",
  "linz:geographic_description": "Ōpōtiki to Tōrere",
  "extent": {
    "spatial": { "bbox": [[177.2276822, -38.1771528, 177.7925909, -37.8327552]] },
    "temporal": { "interval": [["2025-02-23T11:00:00Z", "2025-03-27T11:00:00Z"]] }
  },
  "assets": {
    "capture_area": {
      "href": "./capture-area.geojson",
      "title": "Capture area",
      "description": "Boundary of the total capture area for this collection provided by the data supplier. May include some areas of nodata where capture was attempted but unsuccessful. Geometries are simplified.",
      "type": "application/geo+json",
      "roles": ["metadata"],
      "file:checksum": "1220b30af57317ea4fef0dfbc8d9f4494e51ffa43afef85bad519f6406dd2bac469b",
      "file:size": 36986222
    }
  },
  "stac_extensions": ["https://stac-extensions.github.io/file/v2.0.0/schema.json"]
}
