{
  "type": "Collection",
  "stac_version": "1.0.0",
  "id": "01K4RYMF9YVWBGYKPZ5HAMGWRQ",
  "title": "New Zealand 1m DSM Hillshade",
  "description": "Hillshade generated from the New Zealand LiDAR 1m DSM using GDAL’s default hillshading parameters of 315˚ azimuth and 45˚ elevation angle.",
  "license": "CC-BY-4.0",
  "links": [
    {
      "rel": "root",
      "href": "https://nz-coastal.s3.ap-southeast-2.amazonaws.com/catalog.json",
      "type": "application/json"
    },
    { "rel": "self", "href": "./collection.json", "type": "application/json" },
    {
      "href": "./AU26.json",
      "rel": "item",
      "type": "application/geo+json",
      "file:checksum": "12204cc08f62a9e6f01cbbb9d077f4782ba5123a3b4dec1870d1857ab70c24893aea"
    },
    {
      "href": "./AU27.json",
      "rel": "item",
      "type": "application/geo+json",
      "file:checksum": "1220cf90e07aa7f2230de9ec1c4262a1efa55b798ed23aa6dd67f4161bf4058f8f28"
    },
    {
      "href": "./AV27.json",
      "rel": "item",
      "type": "application/geo+json",
      "file:checksum": "1220bf4e712fc9ac6e6835cbaf1c1dc0d8f20b5ac7e461348fb4eb4441792a1474f2"
    },
    {
      "href": "./BP26.json",
      "rel": "item",
      "type": "application/geo+json",
      "file:checksum": "1220759f1574147bad4a9e3f0087b44cdf0932da22f3dd04c0eb8ca73b43a02eeec1"
    },
    {
      "href": "./BP27.json",
      "rel": "item",
      "type": "application/geo+json",
      "file:checksum": "12208dd444de819aee6276e868a91760862bce3accb2c73d959666d65a6e434be68a"
    },
    {
      "href": "./BQ26.json",
      "rel": "item",
      "type": "application/geo+json",
      "file:checksum": "1220b508a216011e54781e3a14a53d65451344bb25fbe21cd3619b11e6efbfc6726a"
    },
    {
      "href": "./BQ27.json",
      "rel": "item",
      "type": "application/geo+json",
      "file:checksum": "12209197cce82db7913a1a58ede1803de95b4bcf198f5bd30e6f2205e2524fa9e0a4"
    }
  ],
  "providers": [
    { "name": "Toitū Te Whenua Land Information New Zealand", "roles": ["host", "licensor", "processor", "producer"] }
  ],
  "linz:lifecycle": "ongoing",
  "linz:geospatial_category": "dsm-hillshade",
  "linz:region": "new-zealand",
  "linz:security_classification": "unclassified",
  "linz:slug": "new-zealand",
  "created": "2025-09-10T04:37:40Z",
  "updated": "2025-09-10T04:37:40Z",
  "extent": {
    "spatial": { "bbox": [[173.1310027, -41.4975302, 173.7188299, -34.6822331]] },
    "temporal": { "interval": [["2025-02-27T11:00:00Z", "2025-03-30T11:00:00Z"]] }
  },
  "assets": {
    "capture_area": {
      "href": "./capture-area.geojson",
      "title": "Capture area",
      "description": "Boundary of the total capture area for this collection. Excludes nodata areas in the source data. Geometries are simplified.",
      "type": "application/geo+json",
      "roles": ["metadata"],
      "file:checksum": "12206de57dac384d8982dcbba487bce0f7e7eac59c4ecba3980fcc196c45e6d633eb",
      "file:size": 209355
    }
  },
  "stac_extensions": ["https://stac-extensions.github.io/file/v2.0.0/schema.json"]
}
